demo.py
finetune.py
deepvog/CheckEllipse.py
deepvog/__init__.py
deepvog/__main__.py
deepvog/bwperim.py
deepvog/draw_ellipse.py
deepvog/ellipses.py
deepvog/eyefitter.py
deepvog/inferer.py
deepvog/intersection.py
deepvog/jobman.py
deepvog/unprojection.py
deepvog/utils.py
deepvog/visualisation.py
deepvog/model/DeepVOG_model.py
deepvog/model/DeepVOG_weights.h5
deepvog/model/test_if_model_work.py
test/__init__.py
test/__main__.py
test/test_draw_ellipse.py
test/test_eyefitter.py
test/test_inferer.py
test/test_unprojection.py
deepvog-1.2.1.dist-info/LICENSE.txt
deepvog-1.2.1.dist-info/METADATA
deepvog-1.2.1.dist-info/WHEEL
deepvog-1.2.1.dist-info/top_level.txt
deepvog-1.2.1.dist-info/RECORD
