Metadata-Version: 2.1
Name: deepvog
Version: 1.2.1
Summary: Deep VOG for gaze estimation
Home-page: https://github.com/pydsgz/DeepVOG
Author: Yuk-Hoi Yiu
Author-email: yyhhoi@gmail.com
License: GNU General Public License v3.0
Classifier: License :: OSI Approved :: GNU General Public License v3 (GPLv3)
Classifier: Programming Language :: Python :: 3
Classifier: Programming Language :: Python :: 3.9
Classifier: Programming Language :: Python :: 3.10
Classifier: Programming Language :: Python :: 3.11
Classifier: Operating System :: OS Independent
Requires-Python: >=3.9.0
License-File: LICENSE.txt
Requires-Dist: numpy >=1.26.4
Requires-Dist: scikit-video >=1.1.11
Requires-Dist: scikit-image >=0.24.0
Requires-Dist: tensorflow >=2.16.0
Requires-Dist: keras >=3.4.0
